wave_front/__init__.py
wave_front/utils.py
wave_front/core/__init__.py
wave_front/core/view_model.py
wave_front/core/wave_app.py
wave_front/data/__init__.py
wave_front/data/crud_repository.py
wave_front/data/multi_tenant_crud_repository.py
wave_front/ui/__init__.py
wave_front/ui/app_page.py
wave_front/ui/card.py
wave_front/ui/components.py
wave_front/ui/heap_analytics.py
wave_front/ui/overlay.py
wave_front/ui/scaffold.py
wave_front-0.0.4.dist-info/METADATA
wave_front-0.0.4.dist-info/WHEEL
wave_front-0.0.4.dist-info/top_level.txt
wave_front-0.0.4.dist-info/RECORD
