Metadata-Version: 2.1
Name: wave-front
Version: 0.0.4
Requires-Dist: h2o-wave==1.6.0
